jarpc/__init__.py
jarpc/abc.py
jarpc/client.py
jarpc/connection.py
jarpc/constants.py
jarpc/enums.py
jarpc/errors.py
jarpc/py.typed
jarpc/request.py
jarpc/response.py
jarpc/server.py
jarpc/slient.py
jarpc/typing.py
tests/__init__.py
tests/unit/__init__.py
tests/unit/client_test.py
tests/unit/constants_test.py
tests/unit/enums_test.py
jarpc-0.3.1.dist-info/LICENSE
jarpc-0.3.1.dist-info/METADATA
jarpc-0.3.1.dist-info/WHEEL
jarpc-0.3.1.dist-info/top_level.txt
jarpc-0.3.1.dist-info/RECORD
