Metadata-Version: 2.1
Name: jarpc
Version: 0.3.1
Summary: RPC over redis communication library
Home-page: https://github.com/IOMirea/jarpc
Author: Eugene Ershov
Author-email: fogaprod@gmail.com
License: GPLv3
Platform: UNKNOWN
Classifier: Development Status :: 3 - Alpha
Classifier: Intended Audience :: Developers
Classifier: Programming Language :: Python
Classifier: Programming Language :: Python :: 3
Classifier: Programming Language :: Python :: 3.6
Classifier: Programming Language :: Python :: 3.7
Classifier: Programming Language :: Python :: 3.8
Classifier: Programming Language :: Python :: Implementation :: CPython
Classifier: Programming Language :: Python :: Implementation :: PyPy
Classifier: Operating System :: OS Independent
Classifier: License :: OSI Approved :: GNU General Public License v3 (GPLv3)
Classifier: Natural Language :: English
Classifier: Topic :: Software Development :: Object Brokering
Classifier: Typing :: Typed
Requires-Python: >=3.6
Requires-Dist: aioredis
